{
  "user_query": "show me only 3 course in Machine Learning",
  "execution_results": {
    "coursera": {
      "collection": "Coursera",
      "query": {
        "$or": [
          {
            "Title": {
              "$regex": "\\bMachine Learning\\b",
              "$options": "i"
            }
          },
          {
            "Short Intro": {
              "$regex": "\\bMachine Learning\\b",
              "$options": "i"
            }
          },
          {
            "Skills": {
              "$regex": "\\bMachine Learning\\b",
              "$options": "i"
            }
          },
          {
            "Category": {
              "$regex": "\\bMachine Learning\\b",
              "$options": "i"
            }
          },
          {
            "Sub-Category": {
              "$regex": "\\bMachine Learning\\b",
              "$options": "i"
            }
          },
          {
            "What you learn": {
              "$regex": "\\bMachine Learning\\b",
              "$options": "i"
            }
          }
        ]
      },
      "match_count": 3,
      "used_fallback": false,
      "limit_applied": 3,
      "execution_error": null
    },
    "udacity": {
      "collection": "Udacity",
      "query": {
        "$or": [
          {
            "Title": {
              "$regex": "\\bMachine Learning\\b",
              "$options": "i"
            }
          },
          {
            "Short Intro": {
              "$regex": "\\bMachine Learning\\b",
              "$options": "i"
            }
          },
          {
            "What you learn": {
              "$regex": "\\bMachine Learning\\b",
              "$options": "i"
            }
          },
          {
            "Prequisites": {
              "$regex": "\\bMachine Learning\\b",
              "$options": "i"
            }
          }
        ]
      },
      "match_count": 3,
      "used_fallback": false,
      "limit_applied": 3,
      "execution_error": null
    },
    "simplilearn": {
      "collection": "SimpliLearn",
      "query": {
        "$or": [
          {
            "Title": {
              "$regex": "\\bMachine Learning\\b",
              "$options": "i"
            }
          },
          {
            "Short Intro": {
              "$regex": "\\bMachine Learning\\b",
              "$options": "i"
            }
          },
          {
            "Skills": {
              "$regex": "\\bMachine Learning\\b",
              "$options": "i"
            }
          },
          {
            "Category": {
              "$regex": "\\bMachine Learning\\b",
              "$options": "i"
            }
          }
        ]
      },
      "match_count": 3,
      "used_fallback": false,
      "limit_applied": 3,
      "execution_error": null
    },
    "futurelearn": {
      "collection": "FutureLearn",
      "query": {
        "$or": [
          {
            "Title": {
              "$regex": "\\bMachine Learning\\b",
              "$options": "i"
            }
          },
          {
            "Short Intro": {
              "$regex": "\\bMachine Learning\\b",
              "$options": "i"
            }
          },
          {
            "Category": {
              "$regex": "\\bMachine Learning\\b",
              "$options": "i"
            }
          },
          {
            "Sub-Category": {
              "$regex": "\\bMachine Learning\\b",
              "$options": "i"
            }
          }
        ]
      },
      "match_count": 3,
      "used_fallback": false,
      "limit_applied": 3,
      "execution_error": null
    }
  },
  "timestamp": "2025-11-14T21:16:46.431888"
}